pylint_json2html/__init__.py
pylint_json2html/templates/report.jinja2
pylint_json2html-0.5.0.dist-info/LICENSE
pylint_json2html-0.5.0.dist-info/METADATA
pylint_json2html-0.5.0.dist-info/WHEEL
pylint_json2html-0.5.0.dist-info/entry_points.txt
pylint_json2html-0.5.0.dist-info/top_level.txt
pylint_json2html-0.5.0.dist-info/RECORD
