Metadata-Version: 2.1
Name: pylint-json2html
Version: 0.5.0
Summary: Pylint JSON report to HTML
Home-page: https://github.com/Exirel/pylint-json2html
Author: Florian Strzelecki
Author-email: florian.strzelecki@gmail.com
License: MPL-2.0
Keywords: pylint report quality
Classifier: Development Status :: 4 - Beta
Classifier: Environment :: Console
Classifier: Intended Audience :: Developers
Classifier: License :: OSI Approved :: Mozilla Public License 2.0 (MPL 2.0)
Classifier: Operating System :: OS Independent
Classifier: Programming Language :: Python :: 3 :: Only
Classifier: Programming Language :: Python :: 3.8
Classifier: Programming Language :: Python :: 3.9
Classifier: Programming Language :: Python :: 3.10
Classifier: Programming Language :: Python :: 3.11
Classifier: Topic :: Software Development :: Quality Assurance
License-File: LICENSE
Requires-Dist: pylint >=3.0
Requires-Dist: Jinja2
